pandasaurus/.DS_Store
pandasaurus/__init__.py
pandasaurus/curie_validator.py
pandasaurus/graph/__init__.py
pandasaurus/graph/graph_generator.py
pandasaurus/graph/graph_generator_utils.py
pandasaurus/query.py
pandasaurus/resources/__init__.py
pandasaurus/resources/slim.py
pandasaurus/resources/term.py
pandasaurus/slim_manager.py
pandasaurus/utils/__init__.py
pandasaurus/utils/logging_config.py
pandasaurus/utils/pandasaurus_exceptions.py
pandasaurus/utils/query_utils.py
pandasaurus/utils/sparql_queries.py
pandasaurus-0.3.8.dist-info/LICENSE
pandasaurus-0.3.8.dist-info/METADATA
pandasaurus-0.3.8.dist-info/WHEEL
pandasaurus-0.3.8.dist-info/RECORD
