Metadata-Version: 2.1
Name: pandasaurus
Version: 0.3.8
Summary: Supporting simple queries over ontology annotations in dataframes, using UberGraph queries.
License: http://www.apache.org/licenses/LICENSE-2.0
Author: Ismail Ugur Bayindir
Author-email: ugur@ebi.ac.uk
Requires-Python: >=3.9,<4.0
Classifier: License :: Other/Proprietary License
Classifier: Programming Language :: Python :: 3
Classifier: Programming Language :: Python :: 3.9
Classifier: Programming Language :: Python :: 3.10
Classifier: Programming Language :: Python :: 3.11
Classifier: Programming Language :: Python :: 3.12
Provides-Extra: docs
Requires-Dist: oaklib (==0.5.25)
Requires-Dist: pandas (>=2.0.1,<3.0.0)
Requires-Dist: rdflib (>=6.3.2,<7.0.0)
Requires-Dist: sphinx (>=7.2.6,<8.0.0) ; extra == "docs"
Requires-Dist: sphinx-copybutton (>=0.5.2,<0.6.0) ; extra == "docs"
Requires-Dist: sphinx-rtd-theme (>=1.3.0,<2.0.0) ; extra == "docs"
